compare_form_response_tables.py
reviewer2/__init__.py
reviewer2/__main__.py
reviewer2/data_page.py
reviewer2/main_list.py
reviewer2/save.py
reviewer2/utils.py
reviewer2/icons/favicon.png
reviewer2/templates/data_page.html
reviewer2/templates/main_list.html
reviewer2-0.9.31.dist-info/LICENSE
reviewer2-0.9.31.dist-info/METADATA
reviewer2-0.9.31.dist-info/WHEEL
reviewer2-0.9.31.dist-info/top_level.txt
reviewer2-0.9.31.dist-info/RECORD
