Metadata-Version: 2.1
Name: reviewer2
Version: 0.9.31
Summary: Starts a simple image server that lets you quickly flip through image files from a local directory using your web browser and optionally answering customizable questions about each one
Home-page: https://github.com/broadinstitute/reviewer2
License: MIT
Keywords: curation,NGS,sequencing,STRs,REviewer,read visualization,machine learning
Platform: UNKNOWN
Classifier: Development Status :: 4 - Beta
Classifier: Intended Audience :: Developers
Classifier: License :: OSI Approved :: MIT License
Classifier: Natural Language :: English
Classifier: Programming Language :: Python :: 3
Classifier: Programming Language :: Python :: 3.7
Classifier: Programming Language :: Python :: 3.8
Classifier: Programming Language :: Python :: 3.9
Classifier: Programming Language :: Python :: Implementation :: CPython
Classifier: Programming Language :: Python :: Implementation :: PyPy
Requires-Python: >=3.7
Requires-Dist: configargparse
Requires-Dist: flask
Requires-Dist: flask-cors
Requires-Dist: gunicorn
Requires-Dist: jinja2
Requires-Dist: openpyxl
Requires-Dist: pandas
Requires-Dist: requests
Requires-Dist: wcmatch
Requires-Dist: xlrd
Requires-Dist: xlwt
